ancipher/__init__.py
ancipher/__main__.py
ancipher/anc.py
ancipher-1.0.4.dist-info/METADATA
ancipher-1.0.4.dist-info/WHEEL
ancipher-1.0.4.dist-info/entry_points.txt
ancipher-1.0.4.dist-info/top_level.txt
ancipher-1.0.4.dist-info/RECORD
