Metadata-Version: 2.1
Name: ancipher
Version: 1.0.4
Summary: Alpha Numeric Cipher aka ancihper
Home-page: https://github.com/Divinemonk/ancipher/
Author: Divinemonk
Author-email: <v1b7rc8eb@relay.firefox.com>
License: UNKNOWN
Keywords: python,python3,cipher,ancipher
Platform: UNKNOWN
Classifier: Programming Language :: Python :: 3
Classifier: Operating System :: Unix
Classifier: Operating System :: MacOS :: MacOS X
Classifier: License :: OSI Approved :: MIT License
